levels/__init__.py
levels/level_1_Moon.yaml
levels/level_2_Mars.yaml
spacediner/__init__.py
spacediner/__main__.py
spacediner/activities.py
spacediner/cheats.py
spacediner/cli.py
spacediner/diner.py
spacediner/food.py
spacediner/goals.py
spacediner/guests.py
spacediner/ingredients.py
spacediner/kitchen.py
spacediner/levels.py
spacediner/main.py
spacediner/ptpython.py
spacediner/reviews.py
spacediner/rewards.py
spacediner/run.py
spacediner/save.py
spacediner/settings.py
spacediner/shopping.py
spacediner/skills.py
spacediner/social.py
spacediner/storage.py
spacediner/time.py
spacediner/tutorial.py
space_diner-1.0.4.dist-info/LICENSE
space_diner-1.0.4.dist-info/METADATA
space_diner-1.0.4.dist-info/WHEEL
space_diner-1.0.4.dist-info/entry_points.txt
space_diner-1.0.4.dist-info/top_level.txt
space_diner-1.0.4.dist-info/RECORD
