Metadata-Version: 2.1
Name: space-diner
Version: 1.0.4
Summary: Space Diner is a sci-fi themed, text-based sim game.
Home-page: https://github.com/2e2a/space-diner/
Author: Marta Wierzba
Author-email: marta.wierzba@mailbox.org
License: UNKNOWN
Project-URL: Bug Tracker, https://github.com/2e2a/space-diner/issues
Platform: UNKNOWN
Classifier: Programming Language :: Python :: 3
Classifier: License :: OSI Approved :: GNU General Public License v3 or later (GPLv3+)
Classifier: Operating System :: OS Independent
Classifier: Topic :: Games/Entertainment :: Simulation
Requires-Python: >=3.0
Requires-Dist: PyYaml (>=5)
Requires-Dist: importlib-resources ; python_version < "3.7"
Requires-Dist: pyreadline ; sys_platform == "win32"
